ctfutils/__init__.py
ctfutils/exceptions.py
ctfutils/crypto/__init__.py
ctfutils/crypto/classical.py
ctfutils/crypto/hashing.py
ctfutils/crypto/modern.py
ctfutils/forensics/__init__.py
ctfutils/forensics/files.py
ctfutils/forensics/memory.py
ctfutils/forensics/network.py
ctfutils/misc/__init__.py
ctfutils/misc/converters.py
ctfutils/misc/converters_new.py
ctfutils/misc/converters_old.py
ctfutils/misc/encodings.py
ctfutils/misc/utils.py
ctfutils/stego/__init__.py
ctfutils/stego/audio.py
ctfutils/stego/image.py
ctfutils/stego/text.py
ctfutils-1.0.0.dist-info/licenses/LICENSE (MIT)
tests/__init__.py
tests/test_crypto.py
tests/test_misc.py
ctfutils-1.0.0.dist-info/METADATA
ctfutils-1.0.0.dist-info/WHEEL
ctfutils-1.0.0.dist-info/top_level.txt
ctfutils-1.0.0.dist-info/RECORD
