Metadata-Version: 2.4
Name: ctfutils
Version: 1.0.0
Summary: A comprehensive functional toolkit for CTF (Capture The Flag) competitions - 87 pure functions for crypto, stego, forensics, and more
Home-page: https://github.com/Oxidizerhack/ctfutils
Author: Oxidizerhack
Author-email: Oxidizerhack <jhonnyantoquispe@gmail.com>
Maintainer-email: Oxidizerhack <jhonnyantoquispe@gmail.com>
License: MIT
Project-URL: Homepage, https://github.com/Oxidizerhack/PGR2_Practica7
Project-URL: Repository, https://github.com/Oxidizerhack/PGR2_Practica7
Project-URL: Issues, https://github.com/Oxidizerhack/PGR2_Practica7/issues
Keywords: ctf,cybersecurity,crypto,steganography,forensics,functional-programming,cryptography,hacking,security-tools
Classifier: Development Status :: 5 - Production/Stable
Classifier: Intended Audience :: Developers
Classifier: Intended Audience :: Education
Classifier: Intended Audience :: Information Technology
Classifier: License :: OSI Approved :: MIT License
Classifier: Programming Language :: Python :: 3
Classifier: Programming Language :: Python :: 3.8
Classifier: Programming Language :: Python :: 3.9
Classifier: Programming Language :: Python :: 3.10
Classifier: Programming Language :: Python :: 3.11
Classifier: Programming Language :: Python :: 3.12
Classifier: Topic :: Security :: Cryptography
Classifier: Topic :: Software Development :: Libraries :: Python Modules
Classifier: Typing :: Typed
Requires-Python: >=3.8
License-File: LICENSE (MIT)
Requires-Dist: Pillow>=8.0.0
Requires-Dist: cryptography>=3.0.0
Requires-Dist: requests>=2.25.0
Provides-Extra: dev
Requires-Dist: pytest>=6.0.0; extra == "dev"
Requires-Dist: pytest-cov>=2.0.0; extra == "dev"
Requires-Dist: black>=21.0.0; extra == "dev"
Requires-Dist: flake8>=3.8.0; extra == "dev"
Dynamic: license-file
